[
  {
    "_id": { "$oid": "64b0f3e8c1e2f7b8a5d4e501" },
    "assetId": { "$oid": "64b0f3e8c1e2f7b8a5d4e301" },
    "reportedById": { "$oid": "64b0f3e8c1e2f7b8a5d4e104" },
    "reportedDate": { "$date": "2026-07-12T04:20:00.000Z" },
    "issueDescription": "Macbook screen flickers and shows green lines when hot.",
    "priority": "HIGH",
    "status": "RESOLVED",
    "approvedById": { "$oid": "64b0f3e8c1e2f7b8a5d4e103" },
    "approvalDate": { "$date": "2026-07-12T04:30:00.000Z" },
    "technicianId": { "$oid": "64b0f3e8c1e2f7b8a5d4e109" },
    "maintenanceType": "CORRECTIVE",
    "scheduledDate": { "$date": "2026-07-13T09:00:00.000Z" },
    "completionDate": { "$date": "2026-07-13T14:30:00.000Z" },
    "resolutionDetails": "Replaced internal EDP display cable and LCD panel. Validated graphics tests successfully.",
    "cost": 320.00,
    "createdAt": { "$date": "2026-07-12T04:20:00.000Z" },
    "updatedAt": { "$date": "2026-07-13T14:30:00.000Z" }
  },
  {
    "_id": { "$oid": "64b0f3e8c1e2f7b8a5d4e502" },
    "assetId": { "$oid": "64b0f3e8c1e2f7b8a5d4e304" },
    "reportedById": { "$oid": "64b0f3e8c1e2f7b8a5d4e102" },
    "reportedDate": { "$date": "2026-07-12T05:15:00.000Z" },
    "issueDescription": "Routine dust cleaning and display calibration.",
    "priority": "LOW",
    "status": "TECHNICIAN_ASSIGNED",
    "approvedById": { "$oid": "64b0f3e8c1e2f7b8a5d4e102" },
    "approvalDate": { "$date": "2026-07-12T05:15:00.000Z" },
    "technicianId": { "$oid": "64b0f3e8c1e2f7b8a5d4e109" },
    "maintenanceType": "PREVENTIVE",
    "scheduledDate": { "$date": "2026-07-15T13:00:00.000Z" },
    "completionDate": null,
    "resolutionDetails": null,
    "cost": 0.00,
    "createdAt": { "$date": "2026-07-12T05:15:00.000Z" },
    "updatedAt": { "$date": "2026-07-12T05:20:00.000Z" }
  },
  {
    "_id": { "$oid": "64b0f3e8c1e2f7b8a5d4e503" },
    "assetId": { "$oid": "64b0f3e8c1e2f7b8a5d4e303" },
    "reportedById": { "$oid": "64b0f3e8c1e2f7b8a5d4e108" },
    "reportedDate": { "$date": "2026-07-12T08:00:00.000Z" },
    "issueDescription": "Hydraulic cylinder on the chair has failed. Cannot adjust height.",
    "priority": "MEDIUM",
    "status": "PENDING",
    "approvedById": null,
    "approvalDate": null,
    "technicianId": null,
    "maintenanceType": "CORRECTIVE",
    "scheduledDate": null,
    "completionDate": null,
    "resolutionDetails": null,
    "cost": 0.00,
    "createdAt": { "$date": "2026-07-12T08:00:00.000Z" },
    "updatedAt": { "$date": "2026-07-12T08:00:00.000Z" }
  }
]
